MANIFEST.in
README.rst
setup.py
apidev_sanza.egg-info/PKG-INFO
apidev_sanza.egg-info/SOURCES.txt
apidev_sanza.egg-info/dependency_links.txt
apidev_sanza.egg-info/not-zip-safe
apidev_sanza.egg-info/requires.txt
apidev_sanza.egg-info/top_level.txt
sanza/__init__.py
sanza/bower.json
sanza/config.py
sanza/forms.py
sanza/generic.py
sanza/permissions.py
sanza/settings.py
sanza/urls.py
sanza/utils.py
sanza/views.py
sanza/widgets.py
sanza/Apis/__init__.py
sanza/Apis/models.py
sanza/Apis/resources.py
sanza/Apis/urls.py
sanza/Crm/__init__.py
sanza/Crm/admin.py
sanza/Crm/api.py
sanza/Crm/context_processors.py
sanza/Crm/coop_bar_cfg.py
sanza/Crm/models.py
sanza/Crm/search_forms.py
sanza/Crm/semantic.py
sanza/Crm/serializers.py
sanza/Crm/settings.py
sanza/Crm/signals.py
sanza/Crm/translation.py
sanza/Crm/urls.py
sanza/Crm/utils.py
sanza/Crm/widgets.py
sanza/Crm/fixtures/entity_types.json
sanza/Crm/fixtures/loire.json
sanza/Crm/fixtures/zones.json
sanza/Crm/forms/__init__.py
sanza/Crm/forms/actions.py
sanza/Crm/forms/base.py
sanza/Crm/forms/contacts.py
sanza/Crm/forms/custom_fields.py
sanza/Crm/forms/entities.py
sanza/Crm/forms/groups.py
sanza/Crm/management/__init__.py
sanza/Crm/management/commands/__init__.py
sanza/Crm/management/commands/change_entity_type.py
sanza/Crm/management/commands/find_same_as.py
sanza/Crm/management/commands/rename_individual_entities.py
sanza/Crm/migrations/0001_initial.py
sanza/Crm/migrations/0002_auto__add_field_zonetype_type.py
sanza/Crm/migrations/0003_auto__add_opportunitytype__add_field_opportunity_type__add_field_oppor.py
sanza/Crm/migrations/0004_auto__add_field_opportunitystatus_ordering.py
sanza/Crm/migrations/0005_auto__chg_field_opportunity_end_date__chg_field_opportunity_start_date.py
sanza/Crm/migrations/0006_auto__add_field_opportunity_display_on_board.py
sanza/Crm/migrations/0007_auto__del_field_group_account__add_unique_group_name__del_unique_group.py
sanza/Crm/migrations/0008_auto__add_field_contact_address__add_field_contact_zip_code__add_field.py
sanza/Crm/migrations/0009_auto__add_sameas__add_field_contact_same_as.py
sanza/Crm/migrations/0010_auto__add_field_contact_created__add_field_contact_modified__chg_field.py
