Metadata-Version: 1.1
Name: apidev-sanza
Version: 3.1.5
Summary: Contacts management
Home-page: https://bitbucket.org/ljean/apidev-sanza
Author: Luc Jean
Author-email: ljean@apidev.fr
License: CeCILL 2.1
Platform: UNKNOWN
Classifier: Development Status :: 5 - Production/Stable
Classifier: Environment :: Web Environment
Classifier: Intended Audience :: Information Technology
Classifier: License :: OSI Approved :: GNU General Public License v3 or later (GPLv3+)
Classifier: Operating System :: OS Independent
Classifier: Programming Language :: Python
Classifier: Framework :: Django
Classifier: Natural Language :: English
Classifier: Natural Language :: French
Classifier: Topic :: Office/Business
